paprika_recipe/__init__.py
paprika_recipe/archive.py
paprika_recipe/cmdline.py
paprika_recipe/command.py
paprika_recipe/recipe.py
paprika_recipe/types.py
paprika_recipe/commands/__init__.py
paprika_recipe/commands/create_archive.py
paprika_recipe/commands/extract_archive.py
paprika_recipes/__init__.py
paprika_recipes/archive.py
paprika_recipes/cache.py
paprika_recipes/cmdline.py
paprika_recipes/command.py
paprika_recipes/constants.py
paprika_recipes/exceptions.py
paprika_recipes/recipe.py
paprika_recipes/remote.py
paprika_recipes/types.py
paprika_recipes/utils.py
paprika_recipes/commands/__init__.py
paprika_recipes/commands/create_archive.py
paprika_recipes/commands/create_recipe.py
paprika_recipes/commands/download_recipes.py
paprika_recipes/commands/edit_recipe.py
paprika_recipes/commands/extract_archive.py
paprika_recipes/commands/store_password.py
paprika_recipes/commands/upload_recipes.py
paprika_recipes-2.4.1.dist-info/AUTHORS
paprika_recipes-2.4.1.dist-info/METADATA
paprika_recipes-2.4.1.dist-info/WHEEL
paprika_recipes-2.4.1.dist-info/entry_points.txt
paprika_recipes-2.4.1.dist-info/pbr.json
paprika_recipes-2.4.1.dist-info/top_level.txt
paprika_recipes-2.4.1.dist-info/RECORD
