Metadata-Version: 2.1
Name: paprika-recipes
Version: 2.4.1
Summary: Easily view and edit the contents of exports from the Paprika app.
Home-page: https://github.com/coddingtonbear/paprika-recipes/
Author: Adam Coddington
Author-email: me@adamcoddington.net
License: MIT
Classifier: Development Status :: 4 - Beta
Classifier: Environment :: Console
Classifier: Programming Language :: Python :: 3
License-File: AUTHORS
Requires-Dist: pyyaml (<6.0,>=5.0)
Requires-Dist: requests (<3.0,>=2.0)
Requires-Dist: keyring (<22.0,>=21.0)
Requires-Dist: rich (<13.0,>=12.3.0)
Requires-Dist: questionary (<2.0,>=1.10.0)
Requires-Dist: appdirs (<2.0,>=1.4)
Requires-Dist: typing-extensions (<5.0,>=4.4.0)
